LICENSE
MANIFEST.in
README.md
setup.py
MotherNature.egg-info/PKG-INFO
MotherNature.egg-info/SOURCES.txt
MotherNature.egg-info/dependency_links.txt
MotherNature.egg-info/not-zip-safe
MotherNature.egg-info/requires.txt
MotherNature.egg-info/top_level.txt
mothernature/__init__.py
mothernature/environment.py
tests/__init__.py
tests/env.yml
tests/test.py