Metadata-Version: 1.0
Name: MotherNature
Version: 0.3
Summary: Python Environment Variables Manager
Home-page: https://github.com/femmerling/mothernature
Author: Fauzan Emmerling
Author-email: erich@emfeld.com
License: MIT
Platform: UNKNOWN
